smarti/__init__.py
smarti/check_autowire.py
smarti/class_loader.py
smarti/class_loader_flags.py
smarti/constants.py
smarti/decorator.py
smarti/exceptions.py
smarti/instance_storage.py
smarti-1.2.14.dist-info/LICENSE
smarti-1.2.14.dist-info/METADATA
smarti-1.2.14.dist-info/WHEEL
smarti-1.2.14.dist-info/top_level.txt
smarti-1.2.14.dist-info/RECORD
