Metadata-Version: 2.1
Name: smarti
Version: 1.2.14
Summary: A smart and lightweight dependency injector
Home-page: https://github.com/optzGuitar/smarti
Author: optzGuitar
License-File: LICENSE
